kevastro/__init__.py
kevastro/ds9/__init__.py
kevastro/ds9/regions.py
kevastro-0.4.0.dist-info/METADATA
kevastro-0.4.0.dist-info/WHEEL
kevastro-0.4.0.dist-info/RECORD
